grass_gis_helpers/__init__.py
grass_gis_helpers/cleanup.py
grass_gis_helpers/data_import.py
grass_gis_helpers/general.py
grass_gis_helpers/location.py
grass_gis_helpers/mapset.py
grass_gis_helpers/parallel.py
grass_gis_helpers/raster.py
grass_gis_helpers/tests.py
grass_gis_helpers/tiling.py
grass_gis_helpers/validation.py
grass_gis_helpers/vector.py
grass_gis_helpers/open_geodata_germany/__init__.py
grass_gis_helpers/open_geodata_germany/download_data.py
grass_gis_helpers/open_geodata_germany/federal_state.py
grass_gis_helpers-2.3.5.dist-info/licenses/LICENSE
grass_gis_helpers-2.3.5.dist-info/METADATA
grass_gis_helpers-2.3.5.dist-info/WHEEL
grass_gis_helpers-2.3.5.dist-info/top_level.txt
grass_gis_helpers-2.3.5.dist-info/RECORD
