Metadata-Version: 2.4
Name: grass_gis_helpers
Version: 2.3.5
Summary: This library provides functions which can be used for developing GRASS GIS addons.
Author-email: Anika Weinmann <weinmann@mundialis.de>, Carmen Tawalika <tawalika@mundialis.de>, Guido Riembauer <riembauer@mundialis.de>, Johannes Halbauer <halbauer@mundialis.de>, Julia Haas <haas@mundialis.de>, Lina Krisztian <krisztian@mundialis.de>, Markus Neteler <neteler@mundialis.de>, Victoria-Leandra Brunn <brunn@mundialis.de>
Maintainer-email: "mundialis GmbH & Co. KG" <info@mundialis.de>
Project-URL: Homepage, https://github.com/mundialis/grass-gis-helpers
Project-URL: Bug Tracker, https://github.com/mundialis/grass-gis-helpers/issues
Classifier: Programming Language :: Python :: 3
Classifier: License :: OSI Approved :: GNU General Public License v3 (GPLv3)
Classifier: Operating System :: OS Independent
Requires-Python: >=3.7
License-File: LICENSE
Requires-Dist: psutil
Requires-Dist: requests
Requires-Dist: wget
Requires-Dist: zipfile_deflate64
Dynamic: license-file
